loci/__init__.py
loci/analytics.py
loci/brs.py
loci/clustering.py
loci/index.py
loci/io.py
loci/mbrs.py
loci/plots.py
loci/set_evolution.py
loci/time_series.py
loci/topics.py
loci_st-0.1.dist-info/LICENSE
loci_st-0.1.dist-info/METADATA
loci_st-0.1.dist-info/WHEEL
loci_st-0.1.dist-info/top_level.txt
loci_st-0.1.dist-info/RECORD
