Metadata-Version: 2.1
Name: loci-st
Version: 0.1
Summary: LOCI is a component providing functionalities for analysing, mining, and visualizing spatial and temporal data.
Home-page: https://github.com/smartdatalake/loci
Author: Alexandros Zeakis, Dimitrios Skoutas, Kostas Patroumpas, Georgios Chatzigeorgakidis, Panagiotis Kalampokis
Author-email: azeakis@athenarc.gr, dskoutas@athenarc.gr, kpatro@athenarc.gr, gchatzi@athenarc.gr, pkalampokis@athenarc.gr
License: UNKNOWN
Platform: UNKNOWN
Requires-Python: >=3.7
License-File: LICENSE
Requires-Dist: Cython (==0.29.10)
Requires-Dist: wheel (==0.33.4)
Requires-Dist: pandas (==1.2.0)
Requires-Dist: geopandas (==0.8.1)
Requires-Dist: mlxtend (==0.18.0)
Requires-Dist: Rtree (==0.9.7)
Requires-Dist: networkx (==2.5.1)
Requires-Dist: folium (==0.11.0)
Requires-Dist: ipycytoscape (==1.2.2)
Requires-Dist: wordcloud (==1.8.1)
Requires-Dist: osmnx (==1.0.0)
Requires-Dist: plotly (==4.14.0)
Requires-Dist: seaborn (==0.11.2)
Requires-Dist: statsmodels (==0.9.0)
Requires-Dist: ruptures (==1.1.5)
Requires-Dist: voila (==0.2.10)
Requires-Dist: hdbscan (==0.8.26)
Requires-Dist: panel (==0.12.4)
